gj_unitrade/__init__.py
gj_unitrade/unitrad.py
gj_unitrade-0.0.2.dist-info/METADATA
gj_unitrade-0.0.2.dist-info/WHEEL
gj_unitrade-0.0.2.dist-info/top_level.txt
gj_unitrade-0.0.2.dist-info/RECORD
