Metadata-Version: 2.1
Name: gj-unitrade
Version: 0.0.2
Summary: unitrad打包
Author: yin
Author-email: 2018209921@qq.com
Requires-Python: >3.6
Requires-Dist: yaml==6.0.2
Requires-Dist: aiohttp==3.11.10
